tenca/__init__.py
tenca/__main__.py
tenca/connection.py
tenca/exceptions.py
tenca/hash_storage.py
tenca/mailinglist.py
tenca/pipelines.py
tenca/templates.py
tenca/settings/__init__.py
tenca/settings/defaults.py
tenca/templateserver/__init__.py
tenca/templateserver/__main__.py
tenca/tests/__init__.py
tenca/tests/__main__.py
tenca/tests/data_test_settings.py
tenca/tests/list_test.py
tenca/tests/tenca_test.py
tenca/tests/test_confirmation.py
tenca/tests/test_connection.py
tenca/tests/test_findlists.py
tenca/tests/test_hash_storage.py
tenca/tests/test_listproperties.py
tenca/tests/test_roles.py
tenca/tests/test_settings.py
tenca/tests/test_templateserver.py
tenca-0.0.3.dist-info/LICENSE
tenca-0.0.3.dist-info/METADATA
tenca-0.0.3.dist-info/WHEEL
tenca-0.0.3.dist-info/top_level.txt
tenca-0.0.3.dist-info/RECORD
