Metadata-Version: 2.1
Name: tenca
Version: 0.0.3
Summary: An eemaill-like interface for mailman3.
Home-page: https://github.com/tzwenn/tenca
Author: Sven Koehler
Author-email: tenca@svenkoehler.de
Project-URL: Bug Tracker, https://github.com/tzwenn/tenca/issues
Classifier: Programming Language :: Python :: 3
Classifier: License :: OSI Approved :: MIT License
Classifier: Operating System :: OS Independent
Requires-Python: >=3.6
License-File: LICENSE
Requires-Dist: mailmanclient>=3.3.2
